Metadata-Version: 1.1
Name: echoUwU
Version: 0.0.1
Summary: Just Echo UwU
Home-page: UNKNOWN
Author: Fabio Grimaldi
Author-email: fabio@fabiogrimaldi.dev
License: MIT
Keywords: echo
Platform: UNKNOWN
Classifier: Development Status :: 5 - Production/Stable
Classifier: Intended Audience :: Education
Classifier: Operating System :: Microsoft :: Windows :: Windows 10
Classifier: License :: OSI Approved :: MIT License
Classifier: Programming Language :: Python :: 3
